Metadata-Version: 1.1
Name: azure-cosmosdb-table
Version: 1.0.5
Summary: Microsoft Azure CosmosDB Table Client Library for Python
Home-page: https://github.com/Azure/azure-cosmosdb-python
Author: Microsoft Corporation
Author-email: ascl@microsoft.com
License: Apache License 2.0
Platform: UNKNOWN
Classifier: Development Status :: 4 - Beta
Classifier: Programming Language :: Python
Classifier: Programming Language :: Python :: 2
Classifier: Programming Language :: Python :: 2.7
Classifier: Programming Language :: Python :: 3
Classifier: Programming Language :: Python :: 3.3
Classifier: Programming Language :: Python :: 3.4
Classifier: Programming Language :: Python :: 3.5
Classifier: Programming Language :: Python :: 3.6
Classifier: License :: OSI Approved :: Apache Software License
